vetpack/__init__.py
vetpack/centroiding.py
vetpack-0.0.dev2.dist-info/LICENSE
vetpack-0.0.dev2.dist-info/METADATA
vetpack-0.0.dev2.dist-info/WHEEL
vetpack-0.0.dev2.dist-info/top_level.txt
vetpack-0.0.dev2.dist-info/RECORD
